uw_panopto_downloader/__init__.py
uw_panopto_downloader/cli/__init__.py
uw_panopto_downloader/cli/app.py
uw_panopto_downloader/cli/convert.py
uw_panopto_downloader/cli/download.py
uw_panopto_downloader/cli/gcp.py
uw_panopto_downloader/cli/query.py
uw_panopto_downloader/cli/utils.py
uw_panopto_downloader/core/__init__.py
uw_panopto_downloader/core/browser.py
uw_panopto_downloader/core/config.py
uw_panopto_downloader/core/converter.py
uw_panopto_downloader/core/database.py
uw_panopto_downloader/core/downloader.py
uw_panopto_downloader/core/gcp_transcriber.py
uw_panopto_downloader/core/storage.py
uw_panopto_downloader/core/transcriber.py
uw_panopto_downloader/utils/__init__.py
uw_panopto_downloader/utils/file.py
uw_panopto_downloader/utils/logging.py
uw_panopto_downloader/utils/network.py
uw_panopto_downloader-1.1.7.dist-info/METADATA
uw_panopto_downloader-1.1.7.dist-info/WHEEL
uw_panopto_downloader-1.1.7.dist-info/entry_points.txt
uw_panopto_downloader-1.1.7.dist-info/licenses/LICENSE
uw_panopto_downloader-1.1.7.dist-info/RECORD
